fill5320/__init__.py
fill5320/__main__.py
fill5320/fill5320.py
fill5320-0.0.12.dist-info/LICENSE
fill5320-0.0.12.dist-info/METADATA
fill5320-0.0.12.dist-info/WHEEL
fill5320-0.0.12.dist-info/top_level.txt
fill5320-0.0.12.dist-info/RECORD
