Metadata-Version: 2.1
Name: fill5320
Version: 0.0.12
Summary: A tool to fill ATF form 5320.20
Home-page: https://github.com/prairiesnpr/5320_filler
Author: PrairieSnpr
Author-email: midnryanmiller@gmail.com
License: UNKNOWN
Platform: UNKNOWN
Classifier: Programming Language :: Python :: 3
Classifier: License :: OSI Approved :: MIT License
Classifier: Operating System :: OS Independent
Requires-Python: >=3.6
Requires-Dist: pdfforms
Requires-Dist: PyPDF2
Requires-Dist: reportlab
